cdk_serverless_clamscan/__init__.py
cdk_serverless_clamscan/py.typed
cdk_serverless_clamscan/_jsii/__init__.py
cdk_serverless_clamscan/_jsii/cdk-serverless-clamscan@2.13.47.jsii.tgz
cdk_serverless_clamscan-2.13.47.dist-info/LICENSE
cdk_serverless_clamscan-2.13.47.dist-info/METADATA
cdk_serverless_clamscan-2.13.47.dist-info/NOTICE
cdk_serverless_clamscan-2.13.47.dist-info/WHEEL
cdk_serverless_clamscan-2.13.47.dist-info/top_level.txt
cdk_serverless_clamscan-2.13.47.dist-info/RECORD
